pyimdb/__init__.py
pyimdb/imdb.py
pyimdb-0.1.3.dist-info/WHEEL
pyimdb-0.1.3.dist-info/METADATA
pyimdb-0.1.3.dist-info/RECORD
